{
    "meta:license": [
        "Copyright 2017 Adobe Systems Incorporated. All rights reserved.",
        "This work is licensed under a Creative Commons Attribution 4.0 International (CC BY 4.0) license",
        "you may not use this file except in compliance with the License. You may obtain a copy",
        "of the License at https://creativecommons.org/licenses/by/4.0/"
    ],
    "$id": "https://ns.adobe.com/xdm/data/webmetrics",
    "$schema": "http://json-schema.org/draft-06/schema#",
    "title": "Web Metrics",
    "type": "object",
    "description": "Quantifiable measures used to track and assess the status of a web activity.",
    "definitions": {
        "webmetrics": {
            "properties": {
                "xdm:pageViews": {
                    "title": "Page Views",
                    "$ref": "https://ns.adobe.com/xdm/data/metric",
                    "description": "Number of views of a web page.\n"
                },
                "xdm:linkClicks": {
                    "title": "Link Clicks",
                    "$ref": "https://ns.adobe.com/xdm/data/metric",
                    "description": "Number of clicks of a web link.\n"
                }
            }
        }
    },
    "allOf": [
        {
            "$ref": "#/definitions/webmetrics"
        }
    ]
}
