{
  "meta:license": [
    "Copyright 2018 Adobe Systems Incorporated. All rights reserved.",
    "This work is licensed under a Creative Commons Attribution 4.0 International (CC BY 4.0) license",
    "you may not use this file except in compliance with the License. You may obtain a copy",
    "of the License at https://creativecommons.org/licenses/by/4.0/"
  ],
  "$id": "https://ns.adobe.com/experience/intelligent-services/journeyai-sendtimeoptimization",
  "$schema": "http://json-schema.org/draft-06/schema#",
  "title": "Journey AI Send Time Optimization",
  "type": "object",
  "description": "Journey AI Send Time Optimization scores provide the time preferences for message deliveries. Higher score means a better outcome (for example email got clicked) is expected, if a message sent at the corresponding hour.",
  "definitions": {
    "journeyaisendtimeoptimization": {
      "properties": {
        "xdm:emailChannel": {
          "title": "emailChannel",
          "description": "Send Time Optimization scores for email channel",
          "type": "object",
          "isRequired": false,
          "properties": {
            "xdm:sendTimeScoreForClick": {
              "title": "sendTimeScoreForClick",
              "description": "scores for 7*24 hours from GMT Monday hour 0 to Sunday hour 23, representing the inclination of the customer clicking on an email's link if it's sent at that hour",
              "type": "array",
              "isRequired": false,
              "minItems": 168,
              "maxItems": 168,
              "items": {
                "type": "number",
                "meta:xdmType": "number"
              },
              "meta:xdmType": "array"
            },
            "xdm:sendTimeScoreForOpen": {
              "title": "sendTimeScoreForOpen",
              "description": "scores for 7*24 hours from GMT Monday hour 0 to Sunday hour 23, representing the inclination of the customer opening an email if it's sent at that hour",
              "type": "array",
              "isRequired": false,
              "minItems": 168,
              "maxItems": 168,
              "items": {
                "type": "number",
                "meta:xdmType": "number"
              },
              "meta:xdmType": "array"
            }
          },
          "meta:xdmType": "object"
        },
        "xdm:pushChannel": {
          "title": "pushChannel",
          "description": "Send Time Optimization scores for push channel",
          "type": "object",
          "isRequired": false,
          "properties": {
            "xdm:sendTimeScoreForOpen": {
              "title": "sendTimeScoreForOpen",
              "description": "score for 7*24 hours from GMT Monday hour 0 to Sunday hour 23, representing the inclination of the customer opening a push notification if it's sent at that hour",
              "type": "array",
              "isRequired": false,
              "minItems": 168,
              "maxItems": 168,
              "items": {
                "type": "number",
                "meta:xdmType": "number"
              },
              "meta:xdmType": "array"
            }
          },
          "meta:xdmType": "object"
        },
        "xdm:scoreInfo": {
          "title": "scoreInfo",
          "description": "model version and score date as a concatenated string",
          "type": "string",
          "isRequired": false,
          "meta:xdmType": "string"
        }
      }
    }
  },
  "allOf": [
    {
      "$ref": "#/definitions/journeyai-sendtimeoptimization"
    }
  ]
}
