{
    "fnName": "or",
    "nodeType": "fnApply",
    "params": [
        {
            "nodeType": "fnApply",
            "fnName": "equals",
            "params": [
                {
                    "nodeType": "fieldLookup",
                    "fieldName": "firstName",
                    "object": {
                        "nodeType": "fieldLookup",
                        "fieldName": "person",
                        "object": {
                            "nodeType": "literal",
                            "literalType": "XDMObject",
                            "value": "profile"
                        }
                    }
                },
                {
                    "literalType": "String",
                    "nodeType": "literal",
                    "value": "Dennis"
                }
            ]
        },
        {
            "nodeType": "fnApply",
            "fnName": "equals",
            "params": [
                {
                    "nodeType": "fieldLookup",
                    "fieldName": "lastName",
                    "object": {
                        "nodeType": "fieldLookup",
                        "fieldName": "person",
                        "object": {
                            "nodeType": "literal",
                            "literalType": "XDMObject",
                            "value": "profile"
                        }
                    }
                },
                {
                    "literalType": "String",
                    "nodeType": "literal",
                    "value": "Kehrig"
                }
            ]
        },
        {
            "nodeType": "select",
            "variables": [
                {
                    "nodeType": "varDecl",
                    "varName": "_",
                    "from": {
                        "nodeType": "fieldLookup",
                        "fieldName": "pushNotificationTokens",
                        "object": {
                            "nodeType": "literal",
                            "literalType": "XDMObject",
                            "value": "profile"
                        }
                    },
                    "where": {
                        "nodeType": "fnCreate",
                        "params": [
                            {
                                "varName": "X1"
                            }
                        ],
                        "body": {
                            "nodeType": "fnApply",
                            "fnName": "equals",
                            "params": [
                                {
                                    "nodeType": "fieldLookup",
                                    "fieldName": "registrationDate",
                                    "object": {
                                        "nodeType": "varRef",
                                        "varName": "X1"
                                    }
                                },
                                {
                                    "literalType": "String",
                                    "nodeType": "literal",
                                    "value": "2/12/2018"
                                }
                            ]
                        }
                    }
                }
            ]
        }
    ]
}
